ycontract/__init__.py
ycontract/_contract.py
ycontract/_in_contract.py
ycontract/_out_contract.py
ycontract/conds.py
ycontract/ycontract.py
ycontract-0.3.3.2.dist-info/LICENSE
ycontract-0.3.3.2.dist-info/WHEEL
ycontract-0.3.3.2.dist-info/METADATA
ycontract-0.3.3.2.dist-info/RECORD
