Metadata-Version: 2.1
Name: ycontract
Version: 0.3.3.2
Summary: Python library for contracts testing
Home-page: https://gitlab.com/yassu/ycontract.py
License: Apache-2.0
Keywords: contract,test
Author: yassu
Author-email: yasu0320.dev@gmail.com
Requires-Python: >=3.7,<4.0
Classifier: Development Status :: 4 - Beta
Classifier: License :: OSI Approved :: Apache Software License
Classifier: Programming Language :: Python
Classifier: Programming Language :: Python :: 3
Classifier: Programming Language :: Python :: 3 :: Only
Classifier: Programming Language :: Python :: 3.7
Classifier: Programming Language :: Python :: 3.8
Classifier: Programming Language :: Python :: 3.9
Classifier: Topic :: Software Development :: Libraries
Project-URL: Repository, https://gitlab.com/yassu/ycontract.py
